restoredb
