Metadata-Version: 1.1
Name: restoredb
Version: 1.1
Summary: Database restoration script to automatically decompress any format and pipe to the right restorer
Home-page: https://github.com/cecton/restoredb.py
Author: Cecile Tonglet
Author-email: cecile.tonglet@gmail.com
License: MIT
Keywords: postgres database dump restore
Platform: UNKNOWN
Classifier: Development Status :: 5 - Production/Stable
Classifier: Topic :: Database
Classifier: License :: OSI Approved :: MIT License
